conformal_clip/__init__.py
conformal_clip/backends.py
conformal_clip/benchmark.py
conformal_clip/conformal.py
conformal_clip/data_utils.py
conformal_clip/image_io.py
conformal_clip/io_github.py
conformal_clip/metrics.py
conformal_clip/viz.py
conformal_clip/wrappers.py
conformal_clip/zero_shot.py
conformal_clip-0.2.0.dist-info/licenses/LICENSE
conformal_clip-0.2.0.dist-info/METADATA
conformal_clip-0.2.0.dist-info/WHEEL
conformal_clip-0.2.0.dist-info/top_level.txt
conformal_clip-0.2.0.dist-info/RECORD
