Metadata-Version: 2.4
Name: conformal-clip
Version: 0.2.0
Summary: Few-shot CLIP classification with conformal prediction and calibrated probabilities
Author-email: "Fadel M. Megahed" <fmegahed@miamioh.edu>, "Ying-Ju (Tessa) Chen" <ychen4@udayton.edu>
Maintainer-email: "Fadel M. Megahed" <fmegahed@miamioh.edu>, "Ying-Ju (Tessa) Chen" <ychen4@udayton.edu>
License: MIT License
Project-URL: Homepage, https://github.com/fmegahed/conformal_clip
Project-URL: Repository, https://github.com/fmegahed/conformal_clip
Project-URL: Documentation, https://fmegahed.github.io/research/conformal_clip/
Project-URL: Bug Tracker, https://github.com/fmegahed/conformal_clip/issues
Keywords: CLIP,OpenCLIP,conformal prediction,few-shot learning,computer vision,timm
Classifier: Development Status :: 4 - Beta
Classifier: Intended Audience :: Science/Research
Classifier: Intended Audience :: Developers
Classifier: Intended Audience :: Manufacturing
Classifier: Programming Language :: Python :: 3
Classifier: Programming Language :: Python :: 3.9
Classifier: Programming Language :: Python :: 3.10
Classifier: Programming Language :: Python :: 3.11
Classifier: Programming Language :: Python :: 3.12
Classifier: Programming Language :: Python :: 3.13
Classifier: License :: OSI Approved :: MIT License
Classifier: Operating System :: OS Independent
Classifier: Topic :: Scientific/Engineering :: Artificial Intelligence
Classifier: Topic :: Scientific/Engineering :: Image Recognition
Requires-Python: >=3.9
License-File: LICENSE
Requires-Dist: open-clip-torch
Requires-Dist: timm
Requires-Dist: transformers
Requires-Dist: pandas
Requires-Dist: scikit-learn
Requires-Dist: matplotlib
Requires-Dist: seaborn
Requires-Dist: hf_xet
Provides-Extra: data
Requires-Dist: conformal-clip-data==0.1.4; extra == "data"
Dynamic: license-file
